use_triton_in_paddle/__init__.py
use_triton_in_paddle/api.py
use_triton_in_paddle/cuda/__init__.py
use_triton_in_paddle/cuda/all_things.py
use_triton_in_paddle/version/__init__.py
use_triton_in_paddle/version/all_things.py
use_triton_in_paddle-0.1.0.dist-info/METADATA
use_triton_in_paddle-0.1.0.dist-info/WHEEL
use_triton_in_paddle-0.1.0.dist-info/top_level.txt
use_triton_in_paddle-0.1.0.dist-info/RECORD
